CHANGELOG.txt
LICENSE.txt
MANIFEST.in
README.txt
main.py
setup.py
chaithramc99_hamming_code_v1.egg-info/PKG-INFO
chaithramc99_hamming_code_v1.egg-info/SOURCES.txt
chaithramc99_hamming_code_v1.egg-info/dependency_links.txt
chaithramc99_hamming_code_v1.egg-info/top_level.txt
lib/__init__.py
lib/hamming.py
test/__init__.py
test/tests.py
utils/__init__.py
utils/exceptions.py
venv/lib/python3.6/site-packages/easy_install.py
venv/lib/python3.6/site-packages/_distutils_hack/__init__.py
venv/lib/python3.6/site-packages/_distutils_hack/override.py
venv/lib/python3.6/site-packages/pip/__init__.py
venv/lib/python3.6/site-packages/pip/__main__.py
venv/lib/python3.6/site-packages/pip-20.3.3.dist-info/LICENSE.txt
venv/lib/python3.6/site-packages/pip-20.3.3.dist-info/entry_points.txt
venv/lib/python3.6/site-packages/pip-20.3.3.dist-info/top_level.txt
venv/lib/python3.6/site-packages/pip/_internal/__init__.py
venv/lib/python3.6/site-packages/pip/_internal/build_env.py
venv/lib/python3.6/site-packages/pip/_internal/cache.py
venv/lib/python3.6/site-packages/pip/_internal/configuration.py
venv/lib/python3.6/site-packages/pip/_internal/exceptions.py
venv/lib/python3.6/site-packages/pip/_internal/locations.py
venv/lib/python3.6/site-packages/pip/_internal/main.py
venv/lib/python3.6/site-packages/pip/_internal/pyproject.py
venv/lib/python3.6/site-packages/pip/_internal/self_outdated_check.py
venv/lib/python3.6/site-packages/pip/_internal/wheel_builder.py
venv/lib/python3.6/site-packages/pip/_internal/cli/__init__.py
venv/lib/python3.6/site-packages/pip/_internal/cli/autocompletion.py
venv/lib/python3.6/site-packages/pip/_internal/cli/base_command.py
venv/lib/python3.6/site-packages/pip/_internal/cli/cmdoptions.py
venv/lib/python3.6/site-packages/pip/_internal/cli/command_context.py
venv/lib/python3.6/site-packages/pip/_internal/cli/main.py
venv/lib/python3.6/site-packages/pip/_internal/cli/main_parser.py
venv/lib/python3.6/site-packages/pip/_internal/cli/parser.py
venv/lib/python3.6/site-packages/pip/_internal/cli/progress_bars.py
venv/lib/python3.6/site-packages/pip/_internal/cli/req_command.py
venv/lib/python3.6/site-packages/pip/_internal/cli/spinners.py
venv/lib/python3.6/site-packages/pip/_internal/cli/status_codes.py
venv/lib/python3.6/site-packages/pip/_internal/commands/__init__.py
venv/lib/python3.6/site-packages/pip/_internal/commands/cache.py
venv/lib/python3.6/site-packages/setuptools-51.3.1.dist-info/dependency_links.txt
venv/lib/python3.6/site-packages/setuptools-51.3.1.dist-info/entry_points.txt
venv/lib/python3.6/site-packages/setuptools-51.3.1.dist-info/top_level.txt
