Metadata-Version: 1.1
Name: chaithramc99-hamming-code-v1
Version: 0.0.1
Summary: Hamming code generator and validator
Home-page: UNKNOWN
Author: Chaithra M C
Author-email: chaithra.mc99@gmail.com
License: MIT
Keywords: hamming
Platform: UNKNOWN
Classifier: Development Status :: 5 - Production/Stable
Classifier: Intended Audience :: Education
Classifier: Operating System :: Microsoft :: Windows :: Windows 10
Classifier: License :: OSI Approved :: MIT License
Classifier: Programming Language :: Python :: 3
